{
  "type": "FeatureCollection",
  "name": "converted_tour",
  "crs": {
    "type": "name",
    "properties": {
      "name": "urn:ogc:def:crs:OGC:1.3:CRS84"
    }
  },
  "features": [
    {
      "type": "Feature",
      "geometry": {
        "type": "Point",
        "coordinates": [
          -82.519946,
          41.948177
        ]
      },
      "properties": {
        "longitude": -82.519946,
        "latitude": 41.948177,
        "sequence": 190,
        "imageAlt": "DeLaurier Homestead",
        "extra": false,
        "id": "p19att",
        "image": "/photos/p19att.jpg",
        "address": "",
        "name": "DeLaurier Homestead",
        "type": "attraction"
      }
    },
    {
      "type": "Feature",
      "properties": {
        "latitude": 41.9316,
        "longitude": -82.513,
        "sequence": 500,
        "imageAlt": "Visitor Centre",
        "extra": false,
        "id": "p50poi",
        "image": "/photos/p50poi.jpg",
        "address": "",
        "name": "Point Pelee National Park Visitor Centre",
        "type": "attraction"
      },
      "geometry": {
        "coordinates": [
          -82.51304675316592,
          41.9316318129286
        ],
        "type": "Point"
      }
    },
    {
      "type": "Feature",
      "properties": {
        "latitude": 41.93506444376595,
        "longitude": -82.50554394251904,
        "sequence": 505,
        "imageAlt": "East Beach (South)",
        "extra": false,
        "id": "p59poi",
        "image": "/photos/p59poi.jpg",
        "address": "",
        "name": "East Beach (South)",
        "type": "beach"
      },
      "geometry": {
        "coordinates": [
          -82.50554394251904,
          41.93506444376595
        ],
        "type": "Point"
      }
    }
  ]
}